{
  "transactions_update_status": "HISTORICAL_UPDATE_COMPLETE",
  "accounts": [
    {
      "account_id": "6oXBB8RgRjiMNOEgOM7VFqMO1jKEVvhp9vyM4",
      "balances": {
        "available": 8741.49,
        "current": 8746.49,
        "limit": null,
        "iso_currency_code": "USD",
        "unofficial_currency_code": null
      },
      "mask": "0000",
      "name": "REGULAR SHARE",
      "official_name": "REGULAR SHARE",
      "type": "depository",
      "subtype": "savings"
    }
  ],
  "added": [
    {
      "account_id": "6oXBB8RgRjiMNOEgOM7VFqMO1jKEVvhp9vyM4",
      "account_owner": null,
      "amount": -13.15,
      "authorized_date": "2025-12-01",
      "authorized_datetime": "2025-12-01 17:59:59+00:00",
      "category": null,
      "category_id": null,
      "check_number": null,
      "counterparties": [],
      "date": "2025-12-01",
      "datetime": "2025-12-01 17:59:59+00:00",
      "iso_currency_code": "USD",
      "location": {
        "address": null,
        "city": null,
        "region": null,
        "postal_code": null,
        "country": null,
        "lat": null,
        "lon": null,
        "store_number": null
      },
      "logo_url": null,
      "merchant_entity_id": null,
      "merchant_name": null,
      "name": "Deposit Dividend 1.850% Annual Percentage Yield Earned 1.87% from 11/01/25 through 11/30/25",
      "payment_channel": "other",
      "payment_meta": {
        "reference_number": null,
        "ppd_id": null,
        "payee": null,
        "by_order_of": null,
        "payer": null,
        "payment_method": null,
        "payment_processor": null,
        "reason": null
      },
      "pending": false,
      "pending_transaction_id": null,
      "personal_finance_category": {
        "confidence_level": "VERY_HIGH",
        "detailed": "INCOME_INTEREST_EARNED",
        "primary": "INCOME",
        "version": "v1"
      },
      "personal_finance_category_icon_url": "https://plaid-category-icons.plaid.com/PFC_INCOME.png",
      "transaction_code": null,
      "transaction_id": "dvOgg7DKDJsVJxydxVNrfzoP3PepgeI1XxNAv",
      "transaction_type": "special",
      "unofficial_currency_code": null,
      "website": null
    },
    {
      "account_id": "6oXBB8RgRjiMNOEgOM7VFqMO1jKEVvhp9vyM4",
      "account_owner": null,
      "amount": -30.0,
      "authorized_date": "2025-12-02",
      "authorized_datetime": "2025-12-02 17:59:59+00:00",
      "category": null,
      "category_id": null,
      "check_number": null,
      "counterparties": [
        {
          "name": "American Airlines",
          "type": "merchant",
          "website": "aa.com",
          "logo_url": "https://plaid-merchant-logos.plaid.com/american_airlines_51.png",
          "confidence_level": "VERY_HIGH",
          "entity_id": "ZzAQOwb4BD8oN46EAO75yYR3y1BWMZ1Y0Q8NQ",
          "phone_number": null
        }
      ],
      "date": "2025-12-02",
      "datetime": "2025-12-02 17:59:59+00:00",
      "iso_currency_code": "USD",
      "location": {
        "address": null,
        "city": null,
        "region": null,
        "postal_code": null,
        "country": null,
        "lat": null,
        "lon": null,
        "store_number": null
      },
      "logo_url": "https://plaid-merchant-logos.plaid.com/american_airlines_51.png",
      "merchant_entity_id": "ZzAQOwb4BD8oN46EAO75yYR3y1BWMZ1Y0Q8NQ",
      "merchant_name": "American Airlines",
      "name": "American Airlines",
      "payment_channel": "other",
      "payment_meta": {
        "reference_number": null,
        "ppd_id": null,
        "payee": null,
        "by_order_of": null,
        "payer": null,
        "payment_method": "ACH",
        "payment_processor": null,
        "reason": null
      },
      "pending": false,
      "pending_transaction_id": null,
      "personal_finance_category": {
        "confidence_level": "VERY_HIGH",
        "detailed": "TRAVEL_FLIGHTS",
        "primary": "TRAVEL",
        "version": "v1"
      },
      "personal_finance_category_icon_url": "https://plaid-category-icons.plaid.com/PFC_TRAVEL.png",
      "transaction_code": null,
      "transaction_id": "w3bjjZAVAeuQmXoAXQ5ZtaKyPy9qJ9sM0j37p",
      "transaction_type": "special",
      "unofficial_currency_code": null,
      "website": "aa.com"
    },
    {
      "account_id": "6oXBB8RgRjiMNOEgOM7VFqMO1jKEVvhp9vyM4",
      "account_owner": null,
      "amount": -3.98,
      "authorized_date": "2025-12-07",
      "authorized_datetime": "2025-12-07 17:59:59+00:00",
      "category": null,
      "category_id": null,
      "check_number": null,
      "counterparties": [],
      "date": "2025-12-07",
      "datetime": "2025-12-07 17:59:59+00:00",
      "iso_currency_code": "USD",
      "location": {
        "address": null,
        "city": null,
        "region": null,
        "postal_code": null,
        "country": null,
        "lat": null,
        "lon": null,
        "store_number": null
      },
      "logo_url": null,
      "merchant_entity_id": null,
      "merchant_name": null,
      "name": "Transfer Deposit: Deposit Bonus Dividend",
      "payment_channel": "other",
      "payment_meta": {
        "reference_number": null,
        "ppd_id": null,
        "payee": null,
        "by_order_of": null,
        "payer": null,
        "payment_method": null,
        "payment_processor": null,
        "reason": null
      },
      "pending": false,
      "pending_transaction_id": null,
      "personal_finance_category": {
        "confidence_level": "VERY_HIGH",
        "detailed": "INCOME_DIVIDENDS",
        "primary": "INCOME",
        "version": "v1"
      },
      "personal_finance_category_icon_url": "https://plaid-category-icons.plaid.com/PFC_INCOME.png",
      "transaction_code": null,
      "transaction_id": "6oXBB8RgRjiMNOEgOM7VFqMv4vLVxLi9g4jnB",
      "transaction_type": "special",
      "unofficial_currency_code": null,
      "website": null
    },
    {
      "account_id": "6oXBB8RgRjiMNOEgOM7VFqMO1jKEVvhp9vyM4",
      "account_owner": null,
      "amount": -30.0,
      "authorized_date": "2025-12-16",
      "authorized_datetime": "2025-12-16 18:00:00+00:00",
      "category": null,
      "category_id": null,
      "check_number": null,
      "counterparties": [
        {
          "name": "American Airlines",
          "type": "merchant",
          "website": "aa.com",
          "logo_url": "https://plaid-merchant-logos.plaid.com/american_airlines_51.png",
          "confidence_level": "VERY_HIGH",
          "entity_id": "ZzAQOwb4BD8oN46EAO75yYR3y1BWMZ1Y0Q8NQ",
          "phone_number": null
        }
      ],
      "date": "2025-12-16",
      "datetime": "2025-12-16 18:00:00+00:00",
      "iso_currency_code": "USD",
      "location": {
        "address": null,
        "city": null,
        "region": null,
        "postal_code": null,
        "country": null,
        "lat": null,
        "lon": null,
        "store_number": null
      },
      "logo_url": "https://plaid-merchant-logos.plaid.com/american_airlines_51.png",
      "merchant_entity_id": "ZzAQOwb4BD8oN46EAO75yYR3y1BWMZ1Y0Q8NQ",
      "merchant_name": "American Airlines",
      "name": "American Airlines",
      "payment_channel": "other",
      "payment_meta": {
        "reference_number": null,
        "ppd_id": null,
        "payee": null,
        "by_order_of": null,
        "payer": null,
        "payment_method": "ACH",
        "payment_processor": null,
        "reason": null
      },
      "pending": false,
      "pending_transaction_id": null,
      "personal_finance_category": {
        "confidence_level": "VERY_HIGH",
        "detailed": "TRAVEL_FLIGHTS",
        "primary": "TRAVEL",
        "version": "v1"
      },
      "personal_finance_category_icon_url": "https://plaid-category-icons.plaid.com/PFC_TRAVEL.png",
      "transaction_code": null,
      "transaction_id": "LvNmmZDeDXs4gJ9aJ4MVFR8P5PXoLXtPbnx5k",
      "transaction_type": "special",
      "unofficial_currency_code": null,
      "website": "aa.com"
    },
    {
      "account_id": "6oXBB8RgRjiMNOEgOM7VFqMO1jKEVvhp9vyM4",
      "account_owner": null,
      "amount": -13.96,
      "authorized_date": "2025-10-01",
      "authorized_datetime": "2025-10-01 16:59:59+00:00",
      "category": null,
      "category_id": null,
      "check_number": null,
      "counterparties": [],
      "date": "2025-10-01",
      "datetime": "2025-10-01 16:59:59+00:00",
      "iso_currency_code": "USD",
      "location": {
        "address": null,
        "city": null,
        "region": null,
        "postal_code": null,
        "country": null,
        "lat": null,
        "lon": null,
        "store_number": null
      },
      "logo_url": null,
      "merchant_entity_id": null,
      "merchant_name": null,
      "name": "Deposit Dividend 2.000% Annual Percentage Yield Earned 2.02% from 09/01/25 through 09/30/25",
      "payment_channel": "other",
      "payment_meta": {
        "reference_number": null,
        "ppd_id": null,
        "payee": null,
        "by_order_of": null,
        "payer": null,
        "payment_method": null,
        "payment_processor": null,
        "reason": null
      },
      "pending": false,
      "pending_transaction_id": null,
      "personal_finance_category": {
        "confidence_level": "VERY_HIGH",
        "detailed": "INCOME_INTEREST_EARNED",
        "primary": "INCOME",
        "version": "v1"
      },
      "personal_finance_category_icon_url": "https://plaid-category-icons.plaid.com/PFC_INCOME.png",
      "transaction_code": null,
      "transaction_id": "5oXEExRbR0im9ogAom7eCxrBr4KxpXtd7gbrL",
      "transaction_type": "special",
      "unofficial_currency_code": null,
      "website": null
    },
    {
      "account_id": "6oXBB8RgRjiMNOEgOM7VFqMO1jKEVvhp9vyM4",
      "account_owner": null,
      "amount": -30.0,
      "authorized_date": "2025-10-07",
      "authorized_datetime": "2025-10-07 16:59:59+00:00",
      "category": null,
      "category_id": null,
      "check_number": null,
      "counterparties": [
        {
          "name": "American Airlines",
          "type": "merchant",
          "website": "aa.com",
          "logo_url": "https://plaid-merchant-logos.plaid.com/american_airlines_51.png",
          "confidence_level": "VERY_HIGH",
          "entity_id": "ZzAQOwb4BD8oN46EAO75yYR3y1BWMZ1Y0Q8NQ",
          "phone_number": null
        }
      ],
      "date": "2025-10-07",
      "datetime": "2025-10-07 16:59:59+00:00",
      "iso_currency_code": "USD",
      "location": {
        "address": null,
        "city": null,
        "region": null,
        "postal_code": null,
        "country": null,
        "lat": null,
        "lon": null,
        "store_number": null
      },
      "logo_url": "https://plaid-merchant-logos.plaid.com/american_airlines_51.png",
      "merchant_entity_id": "ZzAQOwb4BD8oN46EAO75yYR3y1BWMZ1Y0Q8NQ",
      "merchant_name": "American Airlines",
      "name": "American Airlines",
      "payment_channel": "other",
      "payment_meta": {
        "reference_number": null,
        "ppd_id": null,
        "payee": null,
        "by_order_of": null,
        "payer": null,
        "payment_method": "ACH",
        "payment_processor": null,
        "reason": null
      },
      "pending": false,
      "pending_transaction_id": null,
      "personal_finance_category": {
        "confidence_level": "VERY_HIGH",
        "detailed": "TRAVEL_FLIGHTS",
        "primary": "TRAVEL",
        "version": "v1"
      },
      "personal_finance_category_icon_url": "https://plaid-category-icons.plaid.com/PFC_TRAVEL.png",
      "transaction_code": null,
      "transaction_id": "owN11qx8xMuNa5X05NpwiE4O4dmEKLskn6dRJ",
      "transaction_type": "special",
      "unofficial_currency_code": null,
      "website": "aa.com"
    },
    {
      "account_id": "6oXBB8RgRjiMNOEgOM7VFqMO1jKEVvhp9vyM4",
      "account_owner": null,
      "amount": -30.0,
      "authorized_date": "2025-10-21",
      "authorized_datetime": "2025-10-21 16:59:59+00:00",
      "category": null,
      "category_id": null,
      "check_number": null,
      "counterparties": [
        {
          "name": "American Airlines",
          "type": "merchant",
          "website": "aa.com",
          "logo_url": "https://plaid-merchant-logos.plaid.com/american_airlines_51.png",
          "confidence_level": "VERY_HIGH",
          "entity_id": "ZzAQOwb4BD8oN46EAO75yYR3y1BWMZ1Y0Q8NQ",
          "phone_number": null
        }
      ],
      "date": "2025-10-21",
      "datetime": "2025-10-21 16:59:59+00:00",
      "iso_currency_code": "USD",
      "location": {
        "address": null,
        "city": null,
        "region": null,
        "postal_code": null,
        "country": null,
        "lat": null,
        "lon": null,
        "store_number": null
      },
      "logo_url": "https://plaid-merchant-logos.plaid.com/american_airlines_51.png",
      "merchant_entity_id": "ZzAQOwb4BD8oN46EAO75yYR3y1BWMZ1Y0Q8NQ",
      "merchant_name": "American Airlines",
      "name": "American Airlines",
      "payment_channel": "other",
      "payment_meta": {
        "reference_number": null,
        "ppd_id": null,
        "payee": null,
        "by_order_of": null,
        "payer": null,
        "payment_method": "ACH",
        "payment_processor": null,
        "reason": null
      },
      "pending": false,
      "pending_transaction_id": null,
      "personal_finance_category": {
        "confidence_level": "VERY_HIGH",
        "detailed": "TRAVEL_FLIGHTS",
        "primary": "TRAVEL",
        "version": "v1"
      },
      "personal_finance_category_icon_url": "https://plaid-category-icons.plaid.com/PFC_TRAVEL.png",
      "transaction_code": null,
      "transaction_id": "bkpKK5636asBao1AoBpDsr989EOr4PFdV5xkq",
      "transaction_type": "special",
      "unofficial_currency_code": null,
      "website": "aa.com"
    },
    {
      "account_id": "6oXBB8RgRjiMNOEgOM7VFqMO1jKEVvhp9vyM4",
      "account_owner": null,
      "amount": -13.47,
      "authorized_date": "2025-11-01",
      "authorized_datetime": "2025-11-01 16:59:59+00:00",
      "category": null,
      "category_id": null,
      "check_number": null,
      "counterparties": [],
      "date": "2025-11-01",
      "datetime": "2025-11-01 16:59:59+00:00",
      "iso_currency_code": "USD",
      "location": {
        "address": null,
        "city": null,
        "region": null,
        "postal_code": null,
        "country": null,
        "lat": null,
        "lon": null,
        "store_number": null
      },
      "logo_url": null,
      "merchant_entity_id": null,
      "merchant_name": null,
      "name": "Deposit Dividend 1.850% Annual Percentage Yield Earned 1.87% from 10/01/25 through 10/31/25",
      "payment_channel": "other",
      "payment_meta": {
        "reference_number": null,
        "ppd_id": null,
        "payee": null,
        "by_order_of": null,
        "payer": null,
        "payment_method": null,
        "payment_processor": null,
        "reason": null
      },
      "pending": false,
      "pending_transaction_id": null,
      "personal_finance_category": {
        "confidence_level": "VERY_HIGH",
        "detailed": "INCOME_INTEREST_EARNED",
        "primary": "INCOME",
        "version": "v1"
      },
      "personal_finance_category_icon_url": "https://plaid-category-icons.plaid.com/PFC_INCOME.png",
      "transaction_code": null,
      "transaction_id": "grOAARqvq5iP56mx6PORtdJLJavdokHbv5Mr8",
      "transaction_type": "special",
      "unofficial_currency_code": null,
      "website": null
    },
    {
      "account_id": "6oXBB8RgRjiMNOEgOM7VFqMO1jKEVvhp9vyM4",
      "account_owner": null,
      "amount": -30.0,
      "authorized_date": "2025-11-04",
      "authorized_datetime": "2025-11-04 17:59:59+00:00",
      "category": null,
      "category_id": null,
      "check_number": null,
      "counterparties": [
        {
          "name": "American Airlines",
          "type": "merchant",
          "website": "aa.com",
          "logo_url": "https://plaid-merchant-logos.plaid.com/american_airlines_51.png",
          "confidence_level": "VERY_HIGH",
          "entity_id": "ZzAQOwb4BD8oN46EAO75yYR3y1BWMZ1Y0Q8NQ",
          "phone_number": null
        }
      ],
      "date": "2025-11-04",
      "datetime": "2025-11-04 17:59:59+00:00",
      "iso_currency_code": "USD",
      "location": {
        "address": null,
        "city": null,
        "region": null,
        "postal_code": null,
        "country": null,
        "lat": null,
        "lon": null,
        "store_number": null
      },
      "logo_url": "https://plaid-merchant-logos.plaid.com/american_airlines_51.png",
      "merchant_entity_id": "ZzAQOwb4BD8oN46EAO75yYR3y1BWMZ1Y0Q8NQ",
      "merchant_name": "American Airlines",
      "name": "American Airlines",
      "payment_channel": "other",
      "payment_meta": {
        "reference_number": null,
        "ppd_id": null,
        "payee": null,
        "by_order_of": null,
        "payer": null,
        "payment_method": "ACH",
        "payment_processor": null,
        "reason": null
      },
      "pending": false,
      "pending_transaction_id": null,
      "personal_finance_category": {
        "confidence_level": "VERY_HIGH",
        "detailed": "TRAVEL_FLIGHTS",
        "primary": "TRAVEL",
        "version": "v1"
      },
      "personal_finance_category_icon_url": "https://plaid-category-icons.plaid.com/PFC_TRAVEL.png",
      "transaction_code": null,
      "transaction_id": "7QXgg5a7arIA3jgBjAbwtm3X3y8mx5Fzax4b8",
      "transaction_type": "special",
      "unofficial_currency_code": null,
      "website": "aa.com"
    },
    {
      "account_id": "6oXBB8RgRjiMNOEgOM7VFqMO1jKEVvhp9vyM4",
      "account_owner": null,
      "amount": -30.0,
      "authorized_date": "2025-11-18",
      "authorized_datetime": "2025-11-18 17:59:59+00:00",
      "category": null,
      "category_id": null,
      "check_number": null,
      "counterparties": [
        {
          "name": "American Airlines",
          "type": "merchant",
          "website": "aa.com",
          "logo_url": "https://plaid-merchant-logos.plaid.com/american_airlines_51.png",
          "confidence_level": "VERY_HIGH",
          "entity_id": "ZzAQOwb4BD8oN46EAO75yYR3y1BWMZ1Y0Q8NQ",
          "phone_number": null
        }
      ],
      "date": "2025-11-18",
      "datetime": "2025-11-18 17:59:59+00:00",
      "iso_currency_code": "USD",
      "location": {
        "address": null,
        "city": null,
        "region": null,
        "postal_code": null,
        "country": null,
        "lat": null,
        "lon": null,
        "store_number": null
      },
      "logo_url": "https://plaid-merchant-logos.plaid.com/american_airlines_51.png",
      "merchant_entity_id": "ZzAQOwb4BD8oN46EAO75yYR3y1BWMZ1Y0Q8NQ",
      "merchant_name": "American Airlines",
      "name": "American Airlines",
      "payment_channel": "other",
      "payment_meta": {
        "reference_number": null,
        "ppd_id": null,
        "payee": null,
        "by_order_of": null,
        "payer": null,
        "payment_method": "ACH",
        "payment_processor": null,
        "reason": null
      },
      "pending": false,
      "pending_transaction_id": null,
      "personal_finance_category": {
        "confidence_level": "VERY_HIGH",
        "detailed": "TRAVEL_FLIGHTS",
        "primary": "TRAVEL",
        "version": "v1"
      },
      "personal_finance_category_icon_url": "https://plaid-category-icons.plaid.com/PFC_TRAVEL.png",
      "transaction_code": null,
      "transaction_id": "9oX997bVbair8mPZmrwpTvO0OYdvZwFrLmPvx",
      "transaction_type": "special",
      "unofficial_currency_code": null,
      "website": "aa.com"
    }
  ],
  "modified": [],
  "removed": [],
  "next_cursor": "CAESJTlvWDk5N2JWYmFpcjhtUFptcndwVHZPME9ZZHZad0ZyTG1QdngaDAjdsLLKBhCAstvhAiIMCN2wssoGEICy2+ECKgwI3bCyygYQgLLb4QI=",
  "has_more": false,
  "request_id": "VTL8qfH48g2ommp"
}